bayesfilter/__init__.py
bayesfilter/distributions.py
bayesfilter/filtering.py
bayesfilter/model.py
bayesfilter/observation.py
bayesfilter/smoothing.py
bayesfilter/test_filtering_smoothing.py
bayesfilter/unscented.py
bayesfilter/utilities.py
bayesfilter/version.py
bayesfilter-0.0.5.dist-info/METADATA
bayesfilter-0.0.5.dist-info/WHEEL
bayesfilter-0.0.5.dist-info/top_level.txt
bayesfilter-0.0.5.dist-info/RECORD
