Metadata-Version: 2.1
Name: bayesfilter
Version: 0.0.5
Summary: A pure Python/NumPy library for Bayesian filtering and smoothing
Home-page: https://github.com/hugohadfield/bayesfilter
Author: Hugo Hadfield
Author-email: hadfield.hugo@gmail.com
License: MIT
Classifier: Development Status :: 3 - Alpha
Classifier: Intended Audience :: Science/Research
Classifier: License :: OSI Approved :: MIT License
Classifier: Programming Language :: Python :: 3
Classifier: Topic :: Scientific/Engineering :: Mathematics
Requires-Python: >=3.6
Requires-Dist: numpy
